LICENSE
README.rst
setup.cfg
setup.py
undname/__init__.py
undname/undname_build.py
undname.egg-info/PKG-INFO
undname.egg-info/SOURCES.txt
undname.egg-info/dependency_links.txt
undname.egg-info/requires.txt
undname.egg-info/top_level.txt
undname/src/msvcrt.h
undname/src/undname.c
undname/src/wine/debug.h